LICENSE
MANIFEST.in
setup.py
twitter_text/__init__.py
twitter_text/autolink.py
twitter_text/extractor.py
twitter_text/highlighter.py
twitter_text/regex.py
twitter_text/unicode.py
twitter_text/validation.py
twitter_text/templatetags/__init__.py
twitter_text/templatetags/twitterize.py
twitter_text_py.egg-info/PKG-INFO
twitter_text_py.egg-info/SOURCES.txt
twitter_text_py.egg-info/dependency_links.txt
twitter_text_py.egg-info/requires.txt
twitter_text_py.egg-info/top_level.txt