Metadata-Version: 1.1
Name: twitter-text-py
Version: 2.0.0
Summary: A library for auto-converting URLs, mentions, hashtags, lists, etc. in Twitter text. Also does tweet validation and search term highlighting.
Home-page: http://github.com/dryan/twitter-text-py
Author: Daniel Ryan
Author-email: dryan@dryan.com
License: BSD
Platform: UNKNOWN
Classifier: Development Status :: 5 - Production/Stable
Classifier: Environment :: Web Environment
Classifier: Intended Audience :: Developers
Classifier: License :: OSI Approved :: BSD License
Classifier: Operating System :: OS Independent
Classifier: Programming Language :: Python
Classifier: Framework :: Django
